.gitignore
README.txt
setup.cfg
setup.py
collective/__init__.py
collective.blobsync.egg-info/PKG-INFO
collective.blobsync.egg-info/SOURCES.txt
collective.blobsync.egg-info/dependency_links.txt
collective.blobsync.egg-info/entry_points.txt
collective.blobsync.egg-info/namespace_packages.txt
collective.blobsync.egg-info/not-zip-safe
collective.blobsync.egg-info/requires.txt
collective.blobsync.egg-info/top_level.txt
collective/blobsync/__init__.py
collective/blobsync/copyblobs.py
collective/blobsync/main.py
collective/blobsync/utils.py
docs/HISTORY.txt