Metadata-Version: 1.1
Name: collective.blobsync
Version: 1.0
Summary: Rsync wrapper for rotated backups
Home-page: http://svn.plone.org/svn/collective/
Author: Steve McMahon
Author-email: steve@dcn.org
License: GPL
Keywords: rsync
Platform: UNKNOWN
Classifier: Programming Language :: Python
